Workbook

Sheet Business Input
A1: Financial Survival Toolkit
A3: Revenue Assumptions
A4: Average Selling Price | B4: 800
A5: Monthly Sales Volume | B5: 30
A7: Cost Assumptions
A8: Variable Cost per Unit | B8: 350
A9: Monthly Fixed cost | B9: 12000
A11: Cash flow Assumptions
A12: % Unpaid invoices | B12: 0.1
A13: Expected Monthly Growth | B13: 0.05

Sheet Cash Flow Model
A1: Cash Flow Model
A2: Month | B2: Revenue | C2: Cash in | D2: Expenses | E2: Closing Balance
A3: Month 1 | B3: ='Business Input'!B4*'Business Input'!B5 -> 24000 | C3: =B3*(1-'Business Input'!B12) -> 21600 | D3: ='Business Input'!B9+('Business Input'!B8*'Business Input'!B5) -> 22500 | E3: =C3-D3 -> -900
A4: Month 2 | B4: =B3*(1+'Business Input'!B13) -> 25200 | C4: =B4*(1-'Business Input'!B12) -> 22680 | D4: =D3 -> 22500 | E4: =E3+C4-D4 -> -720
A5: Month 3 | B5: =B4*(1+'Business Input'!B13) -> 26460 | C5: =B5*(1-'Business Input'!B12) -> 23814 | D5: =D4 -> 22500 | E5: =E4+C5-D5 -> 594

Sheet Profitability Estimator
A1: Profitability Model
A3: Monthly Revenue | B3: ='Business Input'!B4*'Business Input'!B5 -> 24000
A4: Total Variable Cost | B4: ='Business Input'!B8*'Business Input'!B5 -> 10500
A5: Gross profit | B5: =B3-B4 -> 13500 | E5: Variable | F5: =B4 -> 10500
A6: Net Profit | B6: =B5-'Business Input'!B9 -> 1500 | E6: Fixed | F6: ='Business Input'!B9 -> 12000
A8: Break-even Units | B8: ='Business Input'!B9/('Business Input'!B4-'Business Input'!B8) -> 26.666667
A9: Break-even Revenue | B9: =B8*'Business Input'!B4 -> 21333.333

Sheet Risk indicators
A1: Risk Engine
A2: Margin Risk | B2: =IF('Pricing calculator'!B3<0.4,"High Risk","Stable") -> Stable
A3: Profit Risk | B3: =IF('Profitability Estimator'!B6<0,"Loss","Profit") -> Profit
A4: Liquidity Risk | B4: =IF('Cash Flow Model'!E5<0,"Cash Flow Risk","Healthy Cash Flow") -> Healthy Cash Flow

Sheet Pricing calculator
A1: Pricing Calculator
A2: Contribution Margin | B2: ='Business Input'!B4-'Pricing calculator'!B8 -> 800
A3: Margin % | B3: =B2/'Business Input'!B4 -> 1
A5: Pricing Status | B5: =IF(B3<0.4,"Low Margin Risk","Healthy Margin") -> Healthy Margin

Sheet Dashboards
A1: Financial Survival Toolkit
A2: Financial Performance & Risk Overview
